[{"code":"&#34000;","entity":""},{"code":"&#34001;","entity":""},{"code":"&#34002;","entity":""},{"code":"&#34003;","entity":""},{"code":"&#34004;","entity":""},{"code":"&#34005;","entity":""},{"code":"&#34006;","entity":""},{"code":"&#34007;","entity":""},{"code":"&#34008;","entity":""},{"code":"&#34009;","entity":""},{"code":"&#34010;","entity":""},{"code":"&#34011;","entity":""},{"code":"&#34012;","entity":""},{"code":"&#34013;","entity":""},{"code":"&#34014;","entity":""},{"code":"&#34015;","entity":""},{"code":"&#34016;","entity":""},{"code":"&#34017;","entity":""},{"code":"&#34018;","entity":""},{"code":"&#34019;","entity":""},{"code":"&#34020;","entity":""},{"code":"&#34021;","entity":""},{"code":"&#34022;","entity":""},{"code":"&#34023;","entity":""},{"code":"&#34024;","entity":""},{"code":"&#34025;","entity":""},{"code":"&#34026;","entity":""},{"code":"&#34027;","entity":""},{"code":"&#34028;","entity":""},{"code":"&#34029;","entity":""},{"code":"&#34030;","entity":""},{"code":"&#34031;","entity":""},{"code":"&#34032;","entity":""},{"code":"&#34033;","entity":""},{"code":"&#34034;","entity":""},{"code":"&#34035;","entity":""},{"code":"&#34036;","entity":""},{"code":"&#34037;","entity":""},{"code":"&#34038;","entity":""},{"code":"&#34039;","entity":""},{"code":"&#34040;","entity":""},{"code":"&#34041;","entity":""},{"code":"&#34042;","entity":""},{"code":"&#34043;","entity":""},{"code":"&#34044;","entity":""},{"code":"&#34045;","entity":""},{"code":"&#34046;","entity":""},{"code":"&#34047;","entity":""},{"code":"&#34048;","entity":""},{"code":"&#34049;","entity":""},{"code":"&#34050;","entity":""},{"code":"&#34051;","entity":""},{"code":"&#34052;","entity":""},{"code":"&#34053;","entity":""},{"code":"&#34054;","entity":""},{"code":"&#34055;","entity":""},{"code":"&#34056;","entity":""},{"code":"&#34057;","entity":""},{"code":"&#34058;","entity":""},{"code":"&#34059;","entity":""},{"code":"&#34060;","entity":""},{"code":"&#34061;","entity":""},{"code":"&#34062;","entity":""},{"code":"&#34063;","entity":""},{"code":"&#34064;","entity":""},{"code":"&#34065;","entity":""},{"code":"&#34066;","entity":""},{"code":"&#34067;","entity":""},{"code":"&#34068;","entity":""},{"code":"&#34069;","entity":""},{"code":"&#34070;","entity":""},{"code":"&#34071;","entity":""},{"code":"&#34072;","entity":""},{"code":"&#34073;","entity":""},{"code":"&#34074;","entity":""},{"code":"&#34075;","entity":""},{"code":"&#34076;","entity":""},{"code":"&#34077;","entity":""},{"code":"&#34078;","entity":""},{"code":"&#34079;","entity":""},{"code":"&#34080;","entity":""},{"code":"&#34081;","entity":""},{"code":"&#34082;","entity":""},{"code":"&#34083;","entity":""},{"code":"&#34084;","entity":""},{"code":"&#34085;","entity":""},{"code":"&#34086;","entity":""},{"code":"&#34087;","entity":""},{"code":"&#34088;","entity":""},{"code":"&#34089;","entity":""},{"code":"&#34090;","entity":""},{"code":"&#34091;","entity":""},{"code":"&#34092;","entity":""},{"code":"&#34093;","entity":""},{"code":"&#34094;","entity":""},{"code":"&#34095;","entity":""},{"code":"&#34096;","entity":""},{"code":"&#34097;","entity":""},{"code":"&#34098;","entity":""},{"code":"&#34099;","entity":""},{"code":"&#34100;","entity":""},{"code":"&#34101;","entity":""},{"code":"&#34102;","entity":""},{"code":"&#34103;","entity":""},{"code":"&#34104;","entity":""},{"code":"&#34105;","entity":""},{"code":"&#34106;","entity":""},{"code":"&#34107;","entity":""},{"code":"&#34108;","entity":""},{"code":"&#34109;","entity":""},{"code":"&#34110;","entity":""},{"code":"&#34111;","entity":""},{"code":"&#34112;","entity":""},{"code":"&#34113;","entity":""},{"code":"&#34114;","entity":""},{"code":"&#34115;","entity":""},{"code":"&#34116;","entity":""},{"code":"&#34117;","entity":""},{"code":"&#34118;","entity":""},{"code":"&#34119;","entity":""},{"code":"&#34120;","entity":""},{"code":"&#34121;","entity":""},{"code":"&#34122;","entity":""},{"code":"&#34123;","entity":""},{"code":"&#34124;","entity":""},{"code":"&#34125;","entity":""},{"code":"&#34126;","entity":""},{"code":"&#34127;","entity":""},{"code":"&#34128;","entity":""},{"code":"&#34129;","entity":""},{"code":"&#34130;","entity":""},{"code":"&#34131;","entity":""},{"code":"&#34132;","entity":""},{"code":"&#34133;","entity":""},{"code":"&#34134;","entity":""},{"code":"&#34135;","entity":""},{"code":"&#34136;","entity":""},{"code":"&#34137;","entity":""},{"code":"&#34138;","entity":""},{"code":"&#34139;","entity":""},{"code":"&#34140;","entity":""},{"code":"&#34141;","entity":""},{"code":"&#34142;","entity":""},{"code":"&#34143;","entity":""},{"code":"&#34144;","entity":""},{"code":"&#34145;","entity":""},{"code":"&#34146;","entity":""},{"code":"&#34147;","entity":""},{"code":"&#34148;","entity":""},{"code":"&#34149;","entity":""},{"code":"&#34150;","entity":""},{"code":"&#34151;","entity":""},{"code":"&#34152;","entity":""},{"code":"&#34153;","entity":""},{"code":"&#34154;","entity":""},{"code":"&#34155;","entity":""},{"code":"&#34156;","entity":""},{"code":"&#34157;","entity":""},{"code":"&#34158;","entity":""},{"code":"&#34159;","entity":""},{"code":"&#34160;","entity":""},{"code":"&#34161;","entity":""},{"code":"&#34162;","entity":""},{"code":"&#34163;","entity":""},{"code":"&#34164;","entity":""},{"code":"&#34165;","entity":""},{"code":"&#34166;","entity":""},{"code":"&#34167;","entity":""},{"code":"&#34168;","entity":""},{"code":"&#34169;","entity":""},{"code":"&#34170;","entity":""},{"code":"&#34171;","entity":""},{"code":"&#34172;","entity":""},{"code":"&#34173;","entity":""},{"code":"&#34174;","entity":""},{"code":"&#34175;","entity":""},{"code":"&#34176;","entity":""},{"code":"&#34177;","entity":""},{"code":"&#34178;","entity":""},{"code":"&#34179;","entity":""},{"code":"&#34180;","entity":""},{"code":"&#34181;","entity":""},{"code":"&#34182;","entity":""},{"code":"&#34183;","entity":""},{"code":"&#34184;","entity":""},{"code":"&#34185;","entity":""},{"code":"&#34186;","entity":""},{"code":"&#34187;","entity":""},{"code":"&#34188;","entity":""},{"code":"&#34189;","entity":""},{"code":"&#34190;","entity":""},{"code":"&#34191;","entity":""},{"code":"&#34192;","entity":""},{"code":"&#34193;","entity":""},{"code":"&#34194;","entity":""},{"code":"&#34195;","entity":""},{"code":"&#34196;","entity":""},{"code":"&#34197;","entity":""},{"code":"&#34198;","entity":""},{"code":"&#34199;","entity":""},{"code":"&#34200;","entity":""},{"code":"&#34201;","entity":""},{"code":"&#34202;","entity":""},{"code":"&#34203;","entity":""},{"code":"&#34204;","entity":""},{"code":"&#34205;","entity":""},{"code":"&#34206;","entity":""},{"code":"&#34207;","entity":""},{"code":"&#34208;","entity":""},{"code":"&#34209;","entity":""},{"code":"&#34210;","entity":""},{"code":"&#34211;","entity":""},{"code":"&#34212;","entity":""},{"code":"&#34213;","entity":""},{"code":"&#34214;","entity":""},{"code":"&#34215;","entity":""},{"code":"&#34216;","entity":""},{"code":"&#34217;","entity":""},{"code":"&#34218;","entity":""},{"code":"&#34219;","entity":""},{"code":"&#34220;","entity":""},{"code":"&#34221;","entity":""},{"code":"&#34222;","entity":""},{"code":"&#34223;","entity":""},{"code":"&#34224;","entity":""},{"code":"&#34225;","entity":""},{"code":"&#34226;","entity":""},{"code":"&#34227;","entity":""},{"code":"&#34228;","entity":""},{"code":"&#34229;","entity":""},{"code":"&#34230;","entity":""},{"code":"&#34231;","entity":""},{"code":"&#34232;","entity":""},{"code":"&#34233;","entity":""},{"code":"&#34234;","entity":""},{"code":"&#34235;","entity":""},{"code":"&#34236;","entity":""},{"code":"&#34237;","entity":""},{"code":"&#34238;","entity":""},{"code":"&#34239;","entity":""},{"code":"&#34240;","entity":""},{"code":"&#34241;","entity":""},{"code":"&#34242;","entity":""},{"code":"&#34243;","entity":""},{"code":"&#34244;","entity":""},{"code":"&#34245;","entity":""},{"code":"&#34246;","entity":""},{"code":"&#34247;","entity":""},{"code":"&#34248;","entity":""},{"code":"&#34249;","entity":""},{"code":"&#34250;","entity":""},{"code":"&#34251;","entity":""},{"code":"&#34252;","entity":""},{"code":"&#34253;","entity":""},{"code":"&#34254;","entity":""},{"code":"&#34255;","entity":""},{"code":"&#34256;","entity":""},{"code":"&#34257;","entity":""},{"code":"&#34258;","entity":""},{"code":"&#34259;","entity":""},{"code":"&#34260;","entity":""},{"code":"&#34261;","entity":""},{"code":"&#34262;","entity":""},{"code":"&#34263;","entity":""},{"code":"&#34264;","entity":""},{"code":"&#34265;","entity":""},{"code":"&#34266;","entity":""},{"code":"&#34267;","entity":""},{"code":"&#34268;","entity":""},{"code":"&#34269;","entity":""},{"code":"&#34270;","entity":""},{"code":"&#34271;","entity":""},{"code":"&#34272;","entity":""},{"code":"&#34273;","entity":""},{"code":"&#34274;","entity":""},{"code":"&#34275;","entity":""},{"code":"&#34276;","entity":""},{"code":"&#34277;","entity":""},{"code":"&#34278;","entity":""},{"code":"&#34279;","entity":""},{"code":"&#34280;","entity":""},{"code":"&#34281;","entity":""},{"code":"&#34282;","entity":""},{"code":"&#34283;","entity":""},{"code":"&#34284;","entity":""},{"code":"&#34285;","entity":""},{"code":"&#34286;","entity":""},{"code":"&#34287;","entity":""},{"code":"&#34288;","entity":""},{"code":"&#34289;","entity":""},{"code":"&#34290;","entity":""},{"code":"&#34291;","entity":""},{"code":"&#34292;","entity":""},{"code":"&#34293;","entity":""},{"code":"&#34294;","entity":""},{"code":"&#34295;","entity":""},{"code":"&#34296;","entity":""},{"code":"&#34297;","entity":""},{"code":"&#34298;","entity":""},{"code":"&#34299;","entity":""},{"code":"&#34300;","entity":""},{"code":"&#34301;","entity":""},{"code":"&#34302;","entity":""},{"code":"&#34303;","entity":""},{"code":"&#34304;","entity":""},{"code":"&#34305;","entity":""},{"code":"&#34306;","entity":""},{"code":"&#34307;","entity":""},{"code":"&#34308;","entity":""},{"code":"&#34309;","entity":""},{"code":"&#34310;","entity":""},{"code":"&#34311;","entity":""},{"code":"&#34312;","entity":""},{"code":"&#34313;","entity":""},{"code":"&#34314;","entity":""},{"code":"&#34315;","entity":""},{"code":"&#34316;","entity":""},{"code":"&#34317;","entity":""},{"code":"&#34318;","entity":""},{"code":"&#34319;","entity":""},{"code":"&#34320;","entity":""},{"code":"&#34321;","entity":""},{"code":"&#34322;","entity":""},{"code":"&#34323;","entity":""},{"code":"&#34324;","entity":""},{"code":"&#34325;","entity":""},{"code":"&#34326;","entity":""},{"code":"&#34327;","entity":""},{"code":"&#34328;","entity":""},{"code":"&#34329;","entity":""},{"code":"&#34330;","entity":""},{"code":"&#34331;","entity":""},{"code":"&#34332;","entity":""},{"code":"&#34333;","entity":""},{"code":"&#34334;","entity":""},{"code":"&#34335;","entity":""},{"code":"&#34336;","entity":""},{"code":"&#34337;","entity":""},{"code":"&#34338;","entity":""},{"code":"&#34339;","entity":""},{"code":"&#34340;","entity":""},{"code":"&#34341;","entity":""},{"code":"&#34342;","entity":""},{"code":"&#34343;","entity":""},{"code":"&#34344;","entity":""},{"code":"&#34345;","entity":""},{"code":"&#34346;","entity":""},{"code":"&#34347;","entity":""},{"code":"&#34348;","entity":""},{"code":"&#34349;","entity":""},{"code":"&#34350;","entity":""},{"code":"&#34351;","entity":""},{"code":"&#34352;","entity":""},{"code":"&#34353;","entity":""},{"code":"&#34354;","entity":""},{"code":"&#34355;","entity":""},{"code":"&#34356;","entity":""},{"code":"&#34357;","entity":""},{"code":"&#34358;","entity":""},{"code":"&#34359;","entity":""},{"code":"&#34360;","entity":""},{"code":"&#34361;","entity":""},{"code":"&#34362;","entity":""},{"code":"&#34363;","entity":""},{"code":"&#34364;","entity":""},{"code":"&#34365;","entity":""},{"code":"&#34366;","entity":""},{"code":"&#34367;","entity":""},{"code":"&#34368;","entity":""},{"code":"&#34369;","entity":""},{"code":"&#34370;","entity":""},{"code":"&#34371;","entity":""},{"code":"&#34372;","entity":""},{"code":"&#34373;","entity":""},{"code":"&#34374;","entity":""},{"code":"&#34375;","entity":""},{"code":"&#34376;","entity":""},{"code":"&#34377;","entity":""},{"code":"&#34378;","entity":""},{"code":"&#34379;","entity":""},{"code":"&#34380;","entity":""},{"code":"&#34381;","entity":""},{"code":"&#34382;","entity":""},{"code":"&#34383;","entity":""},{"code":"&#34384;","entity":""},{"code":"&#34385;","entity":""},{"code":"&#34386;","entity":""},{"code":"&#34387;","entity":""},{"code":"&#34388;","entity":""},{"code":"&#34389;","entity":""},{"code":"&#34390;","entity":""},{"code":"&#34391;","entity":""},{"code":"&#34392;","entity":""},{"code":"&#34393;","entity":""},{"code":"&#34394;","entity":""},{"code":"&#34395;","entity":""},{"code":"&#34396;","entity":""},{"code":"&#34397;","entity":""},{"code":"&#34398;","entity":""},{"code":"&#34399;","entity":""},{"code":"&#34400;","entity":""},{"code":"&#34401;","entity":""},{"code":"&#34402;","entity":""},{"code":"&#34403;","entity":""},{"code":"&#34404;","entity":""},{"code":"&#34405;","entity":""},{"code":"&#34406;","entity":""},{"code":"&#34407;","entity":""},{"code":"&#34408;","entity":""},{"code":"&#34409;","entity":""},{"code":"&#34410;","entity":""},{"code":"&#34411;","entity":""},{"code":"&#34412;","entity":""},{"code":"&#34413;","entity":""},{"code":"&#34414;","entity":""},{"code":"&#34415;","entity":""},{"code":"&#34416;","entity":""},{"code":"&#34417;","entity":""},{"code":"&#34418;","entity":""},{"code":"&#34419;","entity":""},{"code":"&#34420;","entity":""},{"code":"&#34421;","entity":""},{"code":"&#34422;","entity":""},{"code":"&#34423;","entity":""},{"code":"&#34424;","entity":""},{"code":"&#34425;","entity":""},{"code":"&#34426;","entity":""},{"code":"&#34427;","entity":""},{"code":"&#34428;","entity":""},{"code":"&#34429;","entity":""},{"code":"&#34430;","entity":""},{"code":"&#34431;","entity":""},{"code":"&#34432;","entity":""},{"code":"&#34433;","entity":""},{"code":"&#34434;","entity":""},{"code":"&#34435;","entity":""},{"code":"&#34436;","entity":""},{"code":"&#34437;","entity":""},{"code":"&#34438;","entity":""},{"code":"&#34439;","entity":""},{"code":"&#34440;","entity":""},{"code":"&#34441;","entity":""},{"code":"&#34442;","entity":""},{"code":"&#34443;","entity":""},{"code":"&#34444;","entity":""},{"code":"&#34445;","entity":""},{"code":"&#34446;","entity":""},{"code":"&#34447;","entity":""},{"code":"&#34448;","entity":""},{"code":"&#34449;","entity":""},{"code":"&#34450;","entity":""},{"code":"&#34451;","entity":""},{"code":"&#34452;","entity":""},{"code":"&#34453;","entity":""},{"code":"&#34454;","entity":""},{"code":"&#34455;","entity":""},{"code":"&#34456;","entity":""},{"code":"&#34457;","entity":""},{"code":"&#34458;","entity":""},{"code":"&#34459;","entity":""},{"code":"&#34460;","entity":""},{"code":"&#34461;","entity":""},{"code":"&#34462;","entity":""},{"code":"&#34463;","entity":""},{"code":"&#34464;","entity":""},{"code":"&#34465;","entity":""},{"code":"&#34466;","entity":""},{"code":"&#34467;","entity":""},{"code":"&#34468;","entity":""},{"code":"&#34469;","entity":""},{"code":"&#34470;","entity":""},{"code":"&#34471;","entity":""},{"code":"&#34472;","entity":""},{"code":"&#34473;","entity":""},{"code":"&#34474;","entity":""},{"code":"&#34475;","entity":""},{"code":"&#34476;","entity":""},{"code":"&#34477;","entity":""},{"code":"&#34478;","entity":""},{"code":"&#34479;","entity":""},{"code":"&#34480;","entity":""},{"code":"&#34481;","entity":""},{"code":"&#34482;","entity":""},{"code":"&#34483;","entity":""},{"code":"&#34484;","entity":""},{"code":"&#34485;","entity":""},{"code":"&#34486;","entity":""},{"code":"&#34487;","entity":""},{"code":"&#34488;","entity":""},{"code":"&#34489;","entity":""},{"code":"&#34490;","entity":""},{"code":"&#34491;","entity":""},{"code":"&#34492;","entity":""},{"code":"&#34493;","entity":""},{"code":"&#34494;","entity":""},{"code":"&#34495;","entity":""},{"code":"&#34496;","entity":""},{"code":"&#34497;","entity":""},{"code":"&#34498;","entity":""},{"code":"&#34499;","entity":""},{"code":"&#34500;","entity":""},{"code":"&#34501;","entity":""},{"code":"&#34502;","entity":""},{"code":"&#34503;","entity":""},{"code":"&#34504;","entity":""},{"code":"&#34505;","entity":""},{"code":"&#34506;","entity":""},{"code":"&#34507;","entity":""},{"code":"&#34508;","entity":""},{"code":"&#34509;","entity":""},{"code":"&#34510;","entity":""},{"code":"&#34511;","entity":""},{"code":"&#34512;","entity":""},{"code":"&#34513;","entity":""},{"code":"&#34514;","entity":""},{"code":"&#34515;","entity":""},{"code":"&#34516;","entity":""},{"code":"&#34517;","entity":""},{"code":"&#34518;","entity":""},{"code":"&#34519;","entity":""},{"code":"&#34520;","entity":""},{"code":"&#34521;","entity":""},{"code":"&#34522;","entity":""},{"code":"&#34523;","entity":""},{"code":"&#34524;","entity":""},{"code":"&#34525;","entity":""},{"code":"&#34526;","entity":""},{"code":"&#34527;","entity":""},{"code":"&#34528;","entity":""},{"code":"&#34529;","entity":""},{"code":"&#34530;","entity":""},{"code":"&#34531;","entity":""},{"code":"&#34532;","entity":""},{"code":"&#34533;","entity":""},{"code":"&#34534;","entity":""},{"code":"&#34535;","entity":""},{"code":"&#34536;","entity":""},{"code":"&#34537;","entity":""},{"code":"&#34538;","entity":""},{"code":"&#34539;","entity":""},{"code":"&#34540;","entity":""},{"code":"&#34541;","entity":""},{"code":"&#34542;","entity":""},{"code":"&#34543;","entity":""},{"code":"&#34544;","entity":""},{"code":"&#34545;","entity":""},{"code":"&#34546;","entity":""},{"code":"&#34547;","entity":""},{"code":"&#34548;","entity":""},{"code":"&#34549;","entity":""},{"code":"&#34550;","entity":""},{"code":"&#34551;","entity":""},{"code":"&#34552;","entity":""},{"code":"&#34553;","entity":""},{"code":"&#34554;","entity":""},{"code":"&#34555;","entity":""},{"code":"&#34556;","entity":""},{"code":"&#34557;","entity":""},{"code":"&#34558;","entity":""},{"code":"&#34559;","entity":""},{"code":"&#34560;","entity":""},{"code":"&#34561;","entity":""},{"code":"&#34562;","entity":""},{"code":"&#34563;","entity":""},{"code":"&#34564;","entity":""},{"code":"&#34565;","entity":""},{"code":"&#34566;","entity":""},{"code":"&#34567;","entity":""},{"code":"&#34568;","entity":""},{"code":"&#34569;","entity":""},{"code":"&#34570;","entity":""},{"code":"&#34571;","entity":""},{"code":"&#34572;","entity":""},{"code":"&#34573;","entity":""},{"code":"&#34574;","entity":""},{"code":"&#34575;","entity":""},{"code":"&#34576;","entity":""},{"code":"&#34577;","entity":""},{"code":"&#34578;","entity":""},{"code":"&#34579;","entity":""},{"code":"&#34580;","entity":""},{"code":"&#34581;","entity":""},{"code":"&#34582;","entity":""},{"code":"&#34583;","entity":""},{"code":"&#34584;","entity":""},{"code":"&#34585;","entity":""},{"code":"&#34586;","entity":""},{"code":"&#34587;","entity":""},{"code":"&#34588;","entity":""},{"code":"&#34589;","entity":""},{"code":"&#34590;","entity":""},{"code":"&#34591;","entity":""},{"code":"&#34592;","entity":""},{"code":"&#34593;","entity":""},{"code":"&#34594;","entity":""},{"code":"&#34595;","entity":""},{"code":"&#34596;","entity":""},{"code":"&#34597;","entity":""},{"code":"&#34598;","entity":""},{"code":"&#34599;","entity":""},{"code":"&#34600;","entity":""},{"code":"&#34601;","entity":""},{"code":"&#34602;","entity":""},{"code":"&#34603;","entity":""},{"code":"&#34604;","entity":""},{"code":"&#34605;","entity":""},{"code":"&#34606;","entity":""},{"code":"&#34607;","entity":""},{"code":"&#34608;","entity":""},{"code":"&#34609;","entity":""},{"code":"&#34610;","entity":""},{"code":"&#34611;","entity":""},{"code":"&#34612;","entity":""},{"code":"&#34613;","entity":""},{"code":"&#34614;","entity":""},{"code":"&#34615;","entity":""},{"code":"&#34616;","entity":""},{"code":"&#34617;","entity":""},{"code":"&#34618;","entity":""},{"code":"&#34619;","entity":""},{"code":"&#34620;","entity":""},{"code":"&#34621;","entity":""},{"code":"&#34622;","entity":""},{"code":"&#34623;","entity":""},{"code":"&#34624;","entity":""},{"code":"&#34625;","entity":""},{"code":"&#34626;","entity":""},{"code":"&#34627;","entity":""},{"code":"&#34628;","entity":""},{"code":"&#34629;","entity":""},{"code":"&#34630;","entity":""},{"code":"&#34631;","entity":""},{"code":"&#34632;","entity":""},{"code":"&#34633;","entity":""},{"code":"&#34634;","entity":""},{"code":"&#34635;","entity":""},{"code":"&#34636;","entity":""},{"code":"&#34637;","entity":""},{"code":"&#34638;","entity":""},{"code":"&#34639;","entity":""},{"code":"&#34640;","entity":""},{"code":"&#34641;","entity":""},{"code":"&#34642;","entity":""},{"code":"&#34643;","entity":""},{"code":"&#34644;","entity":""},{"code":"&#34645;","entity":""},{"code":"&#34646;","entity":""},{"code":"&#34647;","entity":""},{"code":"&#34648;","entity":""},{"code":"&#34649;","entity":""},{"code":"&#34650;","entity":""},{"code":"&#34651;","entity":""},{"code":"&#34652;","entity":""},{"code":"&#34653;","entity":""},{"code":"&#34654;","entity":""},{"code":"&#34655;","entity":""},{"code":"&#34656;","entity":""},{"code":"&#34657;","entity":""},{"code":"&#34658;","entity":""},{"code":"&#34659;","entity":""},{"code":"&#34660;","entity":""},{"code":"&#34661;","entity":""},{"code":"&#34662;","entity":""},{"code":"&#34663;","entity":""},{"code":"&#34664;","entity":""},{"code":"&#34665;","entity":""},{"code":"&#34666;","entity":""},{"code":"&#34667;","entity":""},{"code":"&#34668;","entity":""},{"code":"&#34669;","entity":""},{"code":"&#34670;","entity":""},{"code":"&#34671;","entity":""},{"code":"&#34672;","entity":""},{"code":"&#34673;","entity":""},{"code":"&#34674;","entity":""},{"code":"&#34675;","entity":""},{"code":"&#34676;","entity":""},{"code":"&#34677;","entity":""},{"code":"&#34678;","entity":""},{"code":"&#34679;","entity":""},{"code":"&#34680;","entity":""},{"code":"&#34681;","entity":""},{"code":"&#34682;","entity":""},{"code":"&#34683;","entity":""},{"code":"&#34684;","entity":""},{"code":"&#34685;","entity":""},{"code":"&#34686;","entity":""},{"code":"&#34687;","entity":""},{"code":"&#34688;","entity":""},{"code":"&#34689;","entity":""},{"code":"&#34690;","entity":""},{"code":"&#34691;","entity":""},{"code":"&#34692;","entity":""},{"code":"&#34693;","entity":""},{"code":"&#34694;","entity":""},{"code":"&#34695;","entity":""},{"code":"&#34696;","entity":""},{"code":"&#34697;","entity":""},{"code":"&#34698;","entity":""},{"code":"&#34699;","entity":""},{"code":"&#34700;","entity":""},{"code":"&#34701;","entity":""},{"code":"&#34702;","entity":""},{"code":"&#34703;","entity":""},{"code":"&#34704;","entity":""},{"code":"&#34705;","entity":""},{"code":"&#34706;","entity":""},{"code":"&#34707;","entity":""},{"code":"&#34708;","entity":""},{"code":"&#34709;","entity":""},{"code":"&#34710;","entity":""},{"code":"&#34711;","entity":""},{"code":"&#34712;","entity":""},{"code":"&#34713;","entity":""},{"code":"&#34714;","entity":""},{"code":"&#34715;","entity":""},{"code":"&#34716;","entity":""},{"code":"&#34717;","entity":""},{"code":"&#34718;","entity":""},{"code":"&#34719;","entity":""},{"code":"&#34720;","entity":""},{"code":"&#34721;","entity":""},{"code":"&#34722;","entity":""},{"code":"&#34723;","entity":""},{"code":"&#34724;","entity":""},{"code":"&#34725;","entity":""},{"code":"&#34726;","entity":""},{"code":"&#34727;","entity":""},{"code":"&#34728;","entity":""},{"code":"&#34729;","entity":""},{"code":"&#34730;","entity":""},{"code":"&#34731;","entity":""},{"code":"&#34732;","entity":""},{"code":"&#34733;","entity":""},{"code":"&#34734;","entity":""},{"code":"&#34735;","entity":""},{"code":"&#34736;","entity":""},{"code":"&#34737;","entity":""},{"code":"&#34738;","entity":""},{"code":"&#34739;","entity":""},{"code":"&#34740;","entity":""},{"code":"&#34741;","entity":""},{"code":"&#34742;","entity":""},{"code":"&#34743;","entity":""},{"code":"&#34744;","entity":""},{"code":"&#34745;","entity":""},{"code":"&#34746;","entity":""},{"code":"&#34747;","entity":""},{"code":"&#34748;","entity":""},{"code":"&#34749;","entity":""},{"code":"&#34750;","entity":""},{"code":"&#34751;","entity":""},{"code":"&#34752;","entity":""},{"code":"&#34753;","entity":""},{"code":"&#34754;","entity":""},{"code":"&#34755;","entity":""},{"code":"&#34756;","entity":""},{"code":"&#34757;","entity":""},{"code":"&#34758;","entity":""},{"code":"&#34759;","entity":""},{"code":"&#34760;","entity":""},{"code":"&#34761;","entity":""},{"code":"&#34762;","entity":""},{"code":"&#34763;","entity":""},{"code":"&#34764;","entity":""},{"code":"&#34765;","entity":""},{"code":"&#34766;","entity":""},{"code":"&#34767;","entity":""},{"code":"&#34768;","entity":""},{"code":"&#34769;","entity":""},{"code":"&#34770;","entity":""},{"code":"&#34771;","entity":""},{"code":"&#34772;","entity":""},{"code":"&#34773;","entity":""},{"code":"&#34774;","entity":""},{"code":"&#34775;","entity":""},{"code":"&#34776;","entity":""},{"code":"&#34777;","entity":""},{"code":"&#34778;","entity":""},{"code":"&#34779;","entity":""},{"code":"&#34780;","entity":""},{"code":"&#34781;","entity":""},{"code":"&#34782;","entity":""},{"code":"&#34783;","entity":""},{"code":"&#34784;","entity":""},{"code":"&#34785;","entity":""},{"code":"&#34786;","entity":""},{"code":"&#34787;","entity":""},{"code":"&#34788;","entity":""},{"code":"&#34789;","entity":""},{"code":"&#34790;","entity":""},{"code":"&#34791;","entity":""},{"code":"&#34792;","entity":""},{"code":"&#34793;","entity":""},{"code":"&#34794;","entity":""},{"code":"&#34795;","entity":""},{"code":"&#34796;","entity":""},{"code":"&#34797;","entity":""},{"code":"&#34798;","entity":""},{"code":"&#34799;","entity":""},{"code":"&#34800;","entity":""},{"code":"&#34801;","entity":""},{"code":"&#34802;","entity":""},{"code":"&#34803;","entity":""},{"code":"&#34804;","entity":""},{"code":"&#34805;","entity":""},{"code":"&#34806;","entity":""},{"code":"&#34807;","entity":""},{"code":"&#34808;","entity":""},{"code":"&#34809;","entity":""},{"code":"&#34810;","entity":""},{"code":"&#34811;","entity":""},{"code":"&#34812;","entity":""},{"code":"&#34813;","entity":""},{"code":"&#34814;","entity":""},{"code":"&#34815;","entity":""},{"code":"&#34816;","entity":""},{"code":"&#34817;","entity":""},{"code":"&#34818;","entity":""},{"code":"&#34819;","entity":""},{"code":"&#34820;","entity":""},{"code":"&#34821;","entity":""},{"code":"&#34822;","entity":""},{"code":"&#34823;","entity":""},{"code":"&#34824;","entity":""},{"code":"&#34825;","entity":""},{"code":"&#34826;","entity":""},{"code":"&#34827;","entity":""},{"code":"&#34828;","entity":""},{"code":"&#34829;","entity":""},{"code":"&#34830;","entity":""},{"code":"&#34831;","entity":""},{"code":"&#34832;","entity":""},{"code":"&#34833;","entity":""},{"code":"&#34834;","entity":""},{"code":"&#34835;","entity":""},{"code":"&#34836;","entity":""},{"code":"&#34837;","entity":""},{"code":"&#34838;","entity":""},{"code":"&#34839;","entity":""},{"code":"&#34840;","entity":""},{"code":"&#34841;","entity":""},{"code":"&#34842;","entity":""},{"code":"&#34843;","entity":""},{"code":"&#34844;","entity":""},{"code":"&#34845;","entity":""},{"code":"&#34846;","entity":""},{"code":"&#34847;","entity":""},{"code":"&#34848;","entity":""},{"code":"&#34849;","entity":""},{"code":"&#34850;","entity":""},{"code":"&#34851;","entity":""},{"code":"&#34852;","entity":""},{"code":"&#34853;","entity":""},{"code":"&#34854;","entity":""},{"code":"&#34855;","entity":""},{"code":"&#34856;","entity":""},{"code":"&#34857;","entity":""},{"code":"&#34858;","entity":""},{"code":"&#34859;","entity":""},{"code":"&#34860;","entity":""},{"code":"&#34861;","entity":""},{"code":"&#34862;","entity":""},{"code":"&#34863;","entity":""},{"code":"&#34864;","entity":""},{"code":"&#34865;","entity":""},{"code":"&#34866;","entity":""},{"code":"&#34867;","entity":""},{"code":"&#34868;","entity":""},{"code":"&#34869;","entity":""},{"code":"&#34870;","entity":""},{"code":"&#34871;","entity":""},{"code":"&#34872;","entity":""},{"code":"&#34873;","entity":""},{"code":"&#34874;","entity":""},{"code":"&#34875;","entity":""},{"code":"&#34876;","entity":""},{"code":"&#34877;","entity":""},{"code":"&#34878;","entity":""},{"code":"&#34879;","entity":""},{"code":"&#34880;","entity":""},{"code":"&#34881;","entity":""},{"code":"&#34882;","entity":""},{"code":"&#34883;","entity":""},{"code":"&#34884;","entity":""},{"code":"&#34885;","entity":""},{"code":"&#34886;","entity":""},{"code":"&#34887;","entity":""},{"code":"&#34888;","entity":""},{"code":"&#34889;","entity":""},{"code":"&#34890;","entity":""},{"code":"&#34891;","entity":""},{"code":"&#34892;","entity":""},{"code":"&#34893;","entity":""},{"code":"&#34894;","entity":""},{"code":"&#34895;","entity":""},{"code":"&#34896;","entity":""},{"code":"&#34897;","entity":""},{"code":"&#34898;","entity":""},{"code":"&#34899;","entity":""},{"code":"&#34900;","entity":""},{"code":"&#34901;","entity":""},{"code":"&#34902;","entity":""},{"code":"&#34903;","entity":""},{"code":"&#34904;","entity":""},{"code":"&#34905;","entity":""},{"code":"&#34906;","entity":""},{"code":"&#34907;","entity":""},{"code":"&#34908;","entity":""},{"code":"&#34909;","entity":""},{"code":"&#34910;","entity":""},{"code":"&#34911;","entity":""},{"code":"&#34912;","entity":""},{"code":"&#34913;","entity":""},{"code":"&#34914;","entity":""},{"code":"&#34915;","entity":""},{"code":"&#34916;","entity":""},{"code":"&#34917;","entity":""},{"code":"&#34918;","entity":""},{"code":"&#34919;","entity":""},{"code":"&#34920;","entity":""},{"code":"&#34921;","entity":""},{"code":"&#34922;","entity":""},{"code":"&#34923;","entity":""},{"code":"&#34924;","entity":""},{"code":"&#34925;","entity":""},{"code":"&#34926;","entity":""},{"code":"&#34927;","entity":""},{"code":"&#34928;","entity":""},{"code":"&#34929;","entity":""},{"code":"&#34930;","entity":""},{"code":"&#34931;","entity":""},{"code":"&#34932;","entity":""},{"code":"&#34933;","entity":""},{"code":"&#34934;","entity":""},{"code":"&#34935;","entity":""},{"code":"&#34936;","entity":""},{"code":"&#34937;","entity":""},{"code":"&#34938;","entity":""},{"code":"&#34939;","entity":""},{"code":"&#34940;","entity":""},{"code":"&#34941;","entity":""},{"code":"&#34942;","entity":""},{"code":"&#34943;","entity":""},{"code":"&#34944;","entity":""},{"code":"&#34945;","entity":""},{"code":"&#34946;","entity":""},{"code":"&#34947;","entity":""},{"code":"&#34948;","entity":""},{"code":"&#34949;","entity":""},{"code":"&#34950;","entity":""},{"code":"&#34951;","entity":""},{"code":"&#34952;","entity":""},{"code":"&#34953;","entity":""},{"code":"&#34954;","entity":""},{"code":"&#34955;","entity":""},{"code":"&#34956;","entity":""},{"code":"&#34957;","entity":""},{"code":"&#34958;","entity":""},{"code":"&#34959;","entity":""},{"code":"&#34960;","entity":""},{"code":"&#34961;","entity":""},{"code":"&#34962;","entity":""},{"code":"&#34963;","entity":""},{"code":"&#34964;","entity":""},{"code":"&#34965;","entity":""},{"code":"&#34966;","entity":""},{"code":"&#34967;","entity":""},{"code":"&#34968;","entity":""},{"code":"&#34969;","entity":""},{"code":"&#34970;","entity":""},{"code":"&#34971;","entity":""},{"code":"&#34972;","entity":""},{"code":"&#34973;","entity":""},{"code":"&#34974;","entity":""},{"code":"&#34975;","entity":""},{"code":"&#34976;","entity":""},{"code":"&#34977;","entity":""},{"code":"&#34978;","entity":""},{"code":"&#34979;","entity":""},{"code":"&#34980;","entity":""},{"code":"&#34981;","entity":""},{"code":"&#34982;","entity":""},{"code":"&#34983;","entity":""},{"code":"&#34984;","entity":""},{"code":"&#34985;","entity":""},{"code":"&#34986;","entity":""},{"code":"&#34987;","entity":""},{"code":"&#34988;","entity":""},{"code":"&#34989;","entity":""},{"code":"&#34990;","entity":""},{"code":"&#34991;","entity":""},{"code":"&#34992;","entity":""},{"code":"&#34993;","entity":""},{"code":"&#34994;","entity":""},{"code":"&#34995;","entity":""},{"code":"&#34996;","entity":""},{"code":"&#34997;","entity":""},{"code":"&#34998;","entity":""},{"code":"&#34999;","entity":""},{"code":"&#35000;","entity":""}]
